scoped_context/__init__.py
scoped_context/py.typed
scoped_context-0.0.1.dist-info/licenses/LICENSE
scoped_context-0.0.1.dist-info/WHEEL
scoped_context-0.0.1.dist-info/METADATA
scoped_context-0.0.1.dist-info/RECORD
