Metadata-Version: 2.4
Name: scoped-context
Version: 0.0.1
Summary: Use contexts (`with` statements) to manage scopes.
Author: Shunichiro Nomura
Author-email: Shunichiro Nomura <nomura@space.t.u-tokyo.ac.jp>
License-Expression: MIT
License-File: LICENSE
Classifier: Development Status :: 3 - Alpha
Classifier: Programming Language :: Python
Classifier: Programming Language :: Python :: 3.9
Classifier: Programming Language :: Python :: 3.10
Classifier: Programming Language :: Python :: 3.11
Classifier: Programming Language :: Python :: 3.12
Classifier: Programming Language :: Python :: 3.13
Classifier: Programming Language :: Python :: 3 :: Only
Classifier: License :: OSI Approved :: MIT License
Classifier: Typing :: Typed
Requires-Dist: typing-extensions>=4.14.1 ; python_full_version < '3.11'
Requires-Python: >=3.9
Project-URL: Issues, https://github.com/shunichironomura/scoped-context/issues
Project-URL: Repository, https://github.com/shunichironomura/scoped-context
